/*  1 */ package a;public final class d { public byte[] a; public int b; public int c; public long d; public byte[] e; public int f; public int g; public long h; public c i; public final a j; public d() { this(); a a1; this
/*    */       
/*  3 */       .j = this; } public final void a() { // Byte code:
/*    */     //   0: aload_0
/*    */     //   1: getfield i : La/c;
/*    */     //   4: dup
/*    */     //   5: astore_0
/*    */     //   6: ifnonnull -> 10
/*    */     //   9: return
/*    */     //   10: aload_0
/*    */     //   11: getfield a : La/d;
/*    */     //   14: dup
/*    */     //   15: astore_1
/*    */     //   16: getfield e : [B
/*    */     //   19: ifnull -> 2369
/*    */     //   22: aload_1
/*    */     //   23: getfield a : [B
/*    */     //   26: ifnonnull -> 36
/*    */     //   29: aload_1
/*    */     //   30: getfield c : I
/*    */     //   33: ifne -> 2369
/*    */     //   36: aload_1
/*    */     //   37: aload_0
/*    */     //   38: getfield b : I
/*    */     //   41: istore_1
/*    */     //   42: getfield g : I
/*    */     //   45: ifne -> 51
/*    */     //   48: goto -> 2369
/*    */     //   51: iload_1
/*    */     //   52: aload_0
/*    */     //   53: invokevirtual getClass : ()Ljava/lang/Class;
/*    */     //   56: pop
/*    */     //   57: bipush #42
/*    */     //   59: if_icmpne -> 563
/*    */     //   62: aload_0
/*    */     //   63: getfield g : I
/*    */     //   66: iconst_2
/*    */     //   67: if_icmpne -> 407
/*    */     //   70: aload_0
/*    */     //   71: monitorenter
/*    */     //   72: aload_0
/*    */     //   73: getfield c0 : La/e;
/*    */     //   76: ifnonnull -> 98
/*    */     //   79: new a/e
/*    */     //   82: dup
/*    */     //   83: astore_1
/*    */     //   84: invokespecial <init> : ()V
/*    */     //   87: aload_0
/*    */     //   88: aload_1
/*    */     //   89: putfield c0 : La/e;
/*    */     //   92: goto -> 98
/*    */     //   95: goto -> 404
/*    */     //   98: aload_0
/*    */     //   99: getfield c0 : La/e;
/*    */     //   102: dup
/*    */     //   103: astore_1
/*    */     //   104: aload_0
/*    */     //   105: monitorexit
/*    */     //   106: iconst_0
/*    */     //   107: istore_2
/*    */     //   108: getfield a : [B
/*    */     //   111: ifnull -> 116
/*    */     //   114: iconst_4
/*    */     //   115: istore_2
/*    */     //   116: aload_1
/*    */     //   117: getfield b : [B
/*    */     //   120: ifnull -> 128
/*    */     //   123: iload_2
/*    */     //   124: bipush #8
/*    */     //   126: ior
/*    */     //   127: istore_2
/*    */     //   128: aload_1
/*    */     //   129: getfield c : [B
/*    */     //   132: ifnull -> 140
/*    */     //   135: iload_2
/*    */     //   136: bipush #16
/*    */     //   138: ior
/*    */     //   139: istore_2
/*    */     //   140: iconst_0
/*    */     //   141: istore_3
/*    */     //   142: aload_0
/*    */     //   143: getfield D : I
/*    */     //   146: dup
/*    */     //   147: istore #4
/*    */     //   149: iconst_1
/*    */     //   150: if_icmpne -> 158
/*    */     //   153: iconst_4
/*    */     //   154: istore_3
/*    */     //   155: goto -> 167
/*    */     //   158: iload #4
/*    */     //   160: bipush #9
/*    */     //   162: if_icmpne -> 167
/*    */     //   165: iconst_2
/*    */     //   166: istore_3
/*    */     //   167: aload_1
/*    */     //   168: iload_3
/*    */     //   169: iload_2
/*    */     //   170: aload_0
/*    */     //   171: sipush #-29921
/*    */     //   174: invokevirtual b : (I)V
/*    */     //   177: aload_0
/*    */     //   178: bipush #8
/*    */     //   180: invokevirtual a : (B)V
/*    */     //   183: i2b
/*    */     //   184: aload_0
/*    */     //   185: swap
/*    */     //   186: invokevirtual a : (B)V
/*    */     //   189: lconst_0
/*    */     //   190: l2i
/*    */     //   191: i2b
/*    */     //   192: istore_2
/*    */     //   193: aload_0
/*    */     //   194: iload_2
/*    */     //   195: invokevirtual a : (B)V
/*    */     //   198: aload_0
/*    */     //   199: iload_2
/*    */     //   200: invokevirtual a : (B)V
/*    */     //   203: aload_0
/*    */     //   204: iload_2
/*    */     //   205: invokevirtual a : (B)V
/*    */     //   208: aload_0
/*    */     //   209: iload_2
/*    */     //   210: invokevirtual a : (B)V
/*    */     //   213: i2b
/*    */     //   214: aload_0
/*    */     //   215: swap
/*    */     //   216: invokevirtual a : (B)V
/*    */     //   219: sipush #255
/*    */     //   222: i2b
/*    */     //   223: aload_0
/*    */     //   224: swap
/*    */     //   225: invokevirtual a : (B)V
/*    */     //   228: getfield a : [B
/*    */     //   231: dup
/*    */     //   232: astore_2
/*    */     //   233: ifnull -> 293
/*    */     //   236: aload_1
/*    */     //   237: dup
/*    */     //   238: aload_2
/*    */     //   239: arraylength
/*    */     //   240: i2b
/*    */     //   241: aload_0
/*    */     //   242: swap
/*    */     //   243: invokevirtual a : (B)V
/*    */     //   246: getfield a : [B
/*    */     //   249: arraylength
/*    */     //   250: bipush #8
/*    */     //   252: ishr
/*    */     //   253: i2b
/*    */     //   254: aload_0
/*    */     //   255: swap
/*    */     //   256: invokevirtual a : (B)V
/*    */     //   259: getfield a : [B
/*    */     //   262: dup
/*    */     //   263: iconst_0
/*    */     //   264: istore_2
/*    */     //   265: arraylength
/*    */     //   266: istore_3
/*    */     //   267: iload_2
/*    */     //   268: aload_0
/*    */     //   269: getfield c : [B
/*    */     //   272: aload_0
/*    */     //   273: getfield f : I
/*    */     //   276: swap
/*    */     //   277: swap
/*    */     //   278: iload_3
/*    */     //   279: invokestatic arraycopy : (Ljava/lang/Object;ILjava/lang/Object;II)V
/*    */     //   282: aload_0
/*    */     //   283: getfield f : I
/*    */     //   286: iload_3
/*    */     //   287: iadd
/*    */     //   288: aload_0
/*    */     //   289: swap
/*    */     //   290: putfield f : I
/*    */     //   293: aload_1
/*    */     //   294: getfield b : [B
/*    */     //   297: dup
/*    */     //   298: astore_2
/*    */     //   299: ifnull -> 339
/*    */     //   302: aload_2
/*    */     //   303: dup
/*    */     //   304: iconst_0
/*    */     //   305: istore_2
/*    */     //   306: arraylength
/*    */     //   307: istore_3
/*    */     //   308: iload_2
/*    */     //   309: aload_0
/*    */     //   310: getfield c : [B
/*    */     //   313: aload_0
/*    */     //   314: getfield f : I
/*    */     //   317: swap
/*    */     //   318: swap
/*    */     //   319: iload_3
/*    */     //   320: invokestatic arraycopy : (Ljava/lang/Object;ILjava/lang/Object;II)V
/*    */     //   323: aload_0
/*    */     //   324: getfield f : I
/*    */     //   327: iload_3
/*    */     //   328: iadd
/*    */     //   329: aload_0
/*    */     //   330: swap
/*    */     //   331: putfield f : I
/*    */     //   334: aload_0
/*    */     //   335: iconst_0
/*    */     //   336: invokevirtual a : (B)V
/*    */     //   339: aload_1
/*    */     //   340: getfield c : [B
/*    */     //   343: dup
/*    */     //   344: astore_1
/*    */     //   345: ifnull -> 385
/*    */     //   348: aload_1
/*    */     //   349: dup
/*    */     //   350: iconst_0
/*    */     //   351: istore_1
/*    */     //   352: arraylength
/*    */     //   353: istore_2
/*    */     //   354: iload_1
/*    */     //   355: aload_0
/*    */     //   356: getfield c : [B
/*    */     //   359: aload_0
/*    */     //   360: getfield f : I
/*    */     //   363: swap
/*    */     //   364: swap
/*    */     //   365: iload_2
/*    */     //   366: invokestatic arraycopy : (Ljava/lang/Object;ILjava/lang/Object;II)V
/*    */     //   369: aload_0
/*    */     //   370: getfield f : I
/*    */     //   373: iload_2
/*    */     //   374: iadd
/*    */     //   375: aload_0
/*    */     //   376: swap
/*    */     //   377: putfield f : I
/*    */     //   380: aload_0
/*    */     //   381: iconst_0
/*    */     //   382: invokevirtual a : (B)V
/*    */     //   385: aload_0
/*    */     //   386: bipush #113
/*    */     //   388: putfield b : I
/*    */     //   391: aload_0
/*    */     //   392: getfield a : La/d;
/*    */     //   395: getfield j : La/a;
/*    */     //   398: invokevirtual b : ()V
/*    */     //   401: goto -> 563
/*    */     //   404: aload_0
/*    */     //   405: monitorexit
/*    */     //   406: athrow
/*    */     //   407: aload_0
/*    */     //   408: getfield j : I
/*    */     //   411: bipush #8
/*    */     //   413: isub
/*    */     //   414: iconst_4
/*    */     //   415: ishl
/*    */     //   416: bipush #8
/*    */     //   418: iadd
/*    */     //   419: bipush #8
/*    */     //   421: ishl
/*    */     //   422: istore_1
/*    */     //   423: aload_0
/*    */     //   424: getfield D : I
/*    */     //   427: iconst_1
/*    */     //   428: isub
/*    */     //   429: sipush #255
/*    */     //   432: iand
/*    */     //   433: iconst_1
/*    */     //   434: ishr
/*    */     //   435: dup
/*    */     //   436: istore_2
/*    */     //   437: iconst_3
/*    */     //   438: if_icmple -> 443
/*    */     //   441: iconst_3
/*    */     //   442: istore_2
/*    */     //   443: iload_1
/*    */     //   444: iload_2
/*    */     //   445: bipush #6
/*    */     //   447: ishl
/*    */     //   448: ior
/*    */     //   449: istore_1
/*    */     //   450: aload_0
/*    */     //   451: getfield x : I
/*    */     //   454: ifeq -> 462
/*    */     //   457: iload_1
/*    */     //   458: bipush #32
/*    */     //   460: ior
/*    */     //   461: istore_1
/*    */     //   462: iload_1
/*    */     //   463: bipush #31
/*    */     //   465: irem
/*    */     //   466: bipush #31
/*    */     //   468: swap
/*    */     //   469: isub
/*    */     //   470: iload_1
/*    */     //   471: iadd
/*    */     //   472: dup
/*    */     //   473: aload_0
/*    */     //   474: bipush #113
/*    */     //   476: putfield b : I
/*    */     //   479: bipush #8
/*    */     //   481: ishr
/*    */     //   482: i2b
/*    */     //   483: aload_0
/*    */     //   484: swap
/*    */     //   485: invokevirtual a : (B)V
/*    */     //   488: i2b
/*    */     //   489: aload_0
/*    */     //   490: swap
/*    */     //   491: invokevirtual a : (B)V
/*    */     //   494: aload_0
/*    */     //   495: getfield x : I
/*    */     //   498: ifeq -> 553
/*    */     //   501: aload_0
/*    */     //   502: getfield a : La/d;
/*    */     //   505: getfield j : La/a;
/*    */     //   508: invokevirtual a : ()J
/*    */     //   511: dup2
/*    */     //   512: bipush #16
/*    */     //   514: lushr
/*    */     //   515: l2i
/*    */     //   516: dup
/*    */     //   517: bipush #8
/*    */     //   519: ishr
/*    */     //   520: i2b
/*    */     //   521: aload_0
/*    */     //   522: swap
/*    */     //   523: invokevirtual a : (B)V
/*    */     //   526: i2b
/*    */     //   527: aload_0
/*    */     //   528: swap
/*    */     //   529: invokevirtual a : (B)V
/*    */     //   532: ldc2_w 65535
/*    */     //   535: land
/*    */     //   536: l2i
/*    */     //   537: dup
/*    */     //   538: bipush #8
/*    */     //   540: ishr
/*    */     //   541: i2b
/*    */     //   542: aload_0
/*    */     //   543: swap
/*    */     //   544: invokevirtual a : (B)V
/*    */     //   547: i2b
/*    */     //   548: aload_0
/*    */     //   549: swap
/*    */     //   550: invokevirtual a : (B)V
/*    */     //   553: aload_0
/*    */     //   554: getfield a : La/d;
/*    */     //   557: getfield j : La/a;
/*    */     //   560: invokevirtual b : ()V
/*    */     //   563: aload_0
/*    */     //   564: getfield f : I
/*    */     //   567: ifeq -> 595
/*    */     //   570: aload_0
/*    */     //   571: getfield a : La/d;
/*    */     //   574: invokevirtual c : ()V
/*    */     //   577: aload_0
/*    */     //   578: getfield a : La/d;
/*    */     //   581: getfield g : I
/*    */     //   584: ifne -> 603
/*    */     //   587: aload_0
/*    */     //   588: invokevirtual getClass : ()Ljava/lang/Class;
/*    */     //   591: pop
/*    */     //   592: goto -> 2369
/*    */     //   595: aload_0
/*    */     //   596: getfield a : La/d;
/*    */     //   599: getfield c : I
/*    */     //   602: pop
/*    */     //   603: aload_0
/*    */     //   604: getfield b : I
/*    */     //   607: dup
/*    */     //   608: istore_1
/*    */     //   609: sipush #666
/*    */     //   612: if_icmpne -> 628
/*    */     //   615: aload_0
/*    */     //   616: getfield a : La/d;
/*    */     //   619: getfield c : I
/*    */     //   622: ifeq -> 628
/*    */     //   625: goto -> 2369
/*    */     //   628: aload_0
/*    */     //   629: getfield a : La/d;
/*    */     //   632: getfield c : I
/*    */     //   635: ifne -> 652
/*    */     //   638: aload_0
/*    */     //   639: getfield z : I
/*    */     //   642: ifne -> 652
/*    */     //   645: iload_1
/*    */     //   646: sipush #666
/*    */     //   649: if_icmpeq -> 2101
/*    */     //   652: iconst_m1
/*    */     //   653: istore_1
/*    */     //   654: getstatic a/c.d0 : [La/b;
/*    */     //   657: aload_0
/*    */     //   658: getfield D : I
/*    */     //   661: aaload
/*    */     //   662: getfield e : I
/*    */     //   665: dup
/*    */     //   666: istore_2
/*    */     //   667: ifeq -> 1778
/*    */     //   670: iload_2
/*    */     //   671: iconst_1
/*    */     //   672: if_icmpeq -> 1298
/*    */     //   675: iload_2
/*    */     //   676: iconst_2
/*    */     //   677: if_icmpeq -> 683
/*    */     //   680: goto -> 1937
/*    */     //   683: iconst_0
/*    */     //   684: istore_1
/*    */     //   685: aload_0
/*    */     //   686: getfield z : I
/*    */     //   689: sipush #262
/*    */     //   692: if_icmpge -> 766
/*    */     //   695: aload_0
/*    */     //   696: invokevirtual a : ()V
/*    */     //   699: aload_0
/*    */     //   700: getfield z : I
/*    */     //   703: ifne -> 766
/*    */     //   706: aload_0
/*    */     //   707: getfield w : I
/*    */     //   710: ifeq -> 741
/*    */     //   713: aload_0
/*    */     //   714: getfield l : [B
/*    */     //   717: aload_0
/*    */     //   718: getfield x : I
/*    */     //   721: iconst_1
/*    */     //   722: isub
/*    */     //   723: baload
/*    */     //   724: sipush #255
/*    */     //   727: iand
/*    */     //   728: istore_1
/*    */     //   729: aload_0
/*    */     //   730: iconst_0
/*    */     //   731: iload_1
/*    */     //   732: invokevirtual a : (II)Z
/*    */     //   735: pop
/*    */     //   736: aload_0
/*    */     //   737: iconst_0
/*    */     //   738: putfield w : I
/*    */     //   741: aload_0
/*    */     //   742: iconst_1
/*    */     //   743: invokevirtual a : (Z)V
/*    */     //   746: aload_0
/*    */     //   747: getfield a : La/d;
/*    */     //   750: getfield g : I
/*    */     //   753: ifne -> 761
/*    */     //   756: iconst_2
/*    */     //   757: istore_1
/*    */     //   758: goto -> 1937
/*    */     //   761: iconst_3
/*    */     //   762: istore_1
/*    */     //   763: goto -> 1937
/*    */     //   766: aload_0
/*    */     //   767: getfield z : I
/*    */     //   770: iconst_3
/*    */     //   771: if_icmplt -> 845
/*    */     //   774: aload_0
/*    */     //   775: getfield p : I
/*    */     //   778: aload_0
/*    */     //   779: getfield s : I
/*    */     //   782: ishl
/*    */     //   783: aload_0
/*    */     //   784: getfield l : [B
/*    */     //   787: aload_0
/*    */     //   788: getfield x : I
/*    */     //   791: dup
/*    */     //   792: istore_1
/*    */     //   793: iconst_2
/*    */     //   794: iadd
/*    */     //   795: baload
/*    */     //   796: sipush #255
/*    */     //   799: iand
/*    */     //   800: ixor
/*    */     //   801: aload_0
/*    */     //   802: getfield r : I
/*    */     //   805: iand
/*    */     //   806: istore_2
/*    */     //   807: aload_0
/*    */     //   808: iload_2
/*    */     //   809: putfield p : I
/*    */     //   812: aload_0
/*    */     //   813: getfield o : [S
/*    */     //   816: dup
/*    */     //   817: astore_3
/*    */     //   818: iload_2
/*    */     //   819: iload_1
/*    */     //   820: aload_3
/*    */     //   821: iload_2
/*    */     //   822: saload
/*    */     //   823: dup
/*    */     //   824: istore_2
/*    */     //   825: ldc 65535
/*    */     //   827: iand
/*    */     //   828: istore_3
/*    */     //   829: aload_0
/*    */     //   830: getfield n : [S
/*    */     //   833: iload_1
/*    */     //   834: aload_0
/*    */     //   835: getfield k : I
/*    */     //   838: iand
/*    */     //   839: iload_2
/*    */     //   840: sastore
/*    */     //   841: i2s
/*    */     //   842: sastore
/*    */     //   843: iload_3
/*    */     //   844: istore_1
/*    */     //   845: iload_1
/*    */     //   846: aload_0
/*    */     //   847: getfield u : I
/*    */     //   850: istore_2
/*    */     //   851: aload_0
/*    */     //   852: iload_2
/*    */     //   853: putfield A : I
/*    */     //   856: aload_0
/*    */     //   857: getfield y : I
/*    */     //   860: aload_0
/*    */     //   861: swap
/*    */     //   862: putfield v : I
/*    */     //   865: aload_0
/*    */     //   866: iconst_2
/*    */     //   867: putfield u : I
/*    */     //   870: ifeq -> 962
/*    */     //   873: iload_2
/*    */     //   874: aload_0
/*    */     //   875: getfield C : I
/*    */     //   878: if_icmpge -> 962
/*    */     //   881: aload_0
/*    */     //   882: getfield x : I
/*    */     //   885: iload_1
/*    */     //   886: isub
/*    */     //   887: ldc 65535
/*    */     //   889: iand
/*    */     //   890: aload_0
/*    */     //   891: getfield i : I
/*    */     //   894: sipush #262
/*    */     //   897: isub
/*    */     //   898: if_icmpgt -> 962
/*    */     //   901: aload_0
/*    */     //   902: getfield E : I
/*    */     //   905: iconst_2
/*    */     //   906: if_icmpeq -> 919
/*    */     //   909: aload_0
/*    */     //   910: iload_1
/*    */     //   911: invokevirtual a : (I)I
/*    */     //   914: aload_0
/*    */     //   915: swap
/*    */     //   916: putfield u : I
/*    */     //   919: aload_0
/*    */     //   920: getfield u : I
/*    */     //   923: dup
/*    */     //   924: istore_2
/*    */     //   925: iconst_5
/*    */     //   926: if_icmpgt -> 962
/*    */     //   929: aload_0
/*    */     //   930: getfield E : I
/*    */     //   933: iconst_1
/*    */     //   934: if_icmpeq -> 957
/*    */     //   937: iload_2
/*    */     //   938: iconst_3
/*    */     //   939: if_icmpne -> 962
/*    */     //   942: aload_0
/*    */     //   943: getfield x : I
/*    */     //   946: aload_0
/*    */     //   947: getfield y : I
/*    */     //   950: isub
/*    */     //   951: sipush #4096
/*    */     //   954: if_icmple -> 962
/*    */     //   957: aload_0
/*    */     //   958: iconst_2
/*    */     //   959: putfield u : I
/*    */     //   962: aload_0
/*    */     //   963: getfield A : I
/*    */     //   966: dup
/*    */     //   967: istore_2
/*    */     //   968: iconst_3
/*    */     //   969: if_icmplt -> 1196
/*    */     //   972: aload_0
/*    */     //   973: getfield u : I
/*    */     //   976: iload_2
/*    */     //   977: if_icmpgt -> 1196
/*    */     //   980: iload_2
/*    */     //   981: aload_0
/*    */     //   982: getfield x : I
/*    */     //   985: dup
/*    */     //   986: aload_0
/*    */     //   987: getfield z : I
/*    */     //   990: iadd
/*    */     //   991: iconst_3
/*    */     //   992: isub
/*    */     //   993: istore_2
/*    */     //   994: iconst_1
/*    */     //   995: isub
/*    */     //   996: aload_0
/*    */     //   997: getfield v : I
/*    */     //   1000: isub
/*    */     //   1001: istore_3
/*    */     //   1002: iconst_3
/*    */     //   1003: isub
/*    */     //   1004: istore #4
/*    */     //   1006: aload_0
/*    */     //   1007: iload_3
/*    */     //   1008: iload #4
/*    */     //   1010: invokevirtual a : (II)Z
/*    */     //   1013: istore_3
/*    */     //   1014: aload_0
/*    */     //   1015: getfield z : I
/*    */     //   1018: istore #4
/*    */     //   1020: aload_0
/*    */     //   1021: getfield A : I
/*    */     //   1024: dup
/*    */     //   1025: iload #4
/*    */     //   1027: swap
/*    */     //   1028: iconst_1
/*    */     //   1029: isub
/*    */     //   1030: isub
/*    */     //   1031: aload_0
/*    */     //   1032: swap
/*    */     //   1033: putfield z : I
/*    */     //   1036: iconst_2
/*    */     //   1037: isub
/*    */     //   1038: aload_0
/*    */     //   1039: swap
/*    */     //   1040: putfield A : I
/*    */     //   1043: aload_0
/*    */     //   1044: getfield x : I
/*    */     //   1047: dup
/*    */     //   1048: istore #4
/*    */     //   1050: iconst_1
/*    */     //   1051: iadd
/*    */     //   1052: dup
/*    */     //   1053: istore #5
/*    */     //   1055: iload_2
/*    */     //   1056: aload_0
/*    */     //   1057: iload #5
/*    */     //   1059: putfield x : I
/*    */     //   1062: if_icmpgt -> 1138
/*    */     //   1065: aload_0
/*    */     //   1066: getfield p : I
/*    */     //   1069: aload_0
/*    */     //   1070: getfield s : I
/*    */     //   1073: ishl
/*    */     //   1074: aload_0
/*    */     //   1075: getfield l : [B
/*    */     //   1078: iload #4
/*    */     //   1080: iconst_3
/*    */     //   1081: iadd
/*    */     //   1082: baload
/*    */     //   1083: sipush #255
/*    */     //   1086: iand
/*    */     //   1087: ixor
/*    */     //   1088: aload_0
/*    */     //   1089: getfield r : I
/*    */     //   1092: iand
/*    */     //   1093: istore_1
/*    */     //   1094: aload_0
/*    */     //   1095: iload_1
/*    */     //   1096: putfield p : I
/*    */     //   1099: aload_0
/*    */     //   1100: getfield o : [S
/*    */     //   1103: dup
/*    */     //   1104: astore #6
/*    */     //   1106: iload_1
/*    */     //   1107: iload #5
/*    */     //   1109: aload #6
/*    */     //   1111: iload_1
/*    */     //   1112: saload
/*    */     //   1113: dup
/*    */     //   1114: istore_1
/*    */     //   1115: ldc 65535
/*    */     //   1117: iand
/*    */     //   1118: istore #6
/*    */     //   1120: aload_0
/*    */     //   1121: getfield n : [S
/*    */     //   1124: iload #5
/*    */     //   1126: aload_0
/*    */     //   1127: getfield k : I
/*    */     //   1130: iand
/*    */     //   1131: iload_1
/*    */     //   1132: sastore
/*    */     //   1133: i2s
/*    */     //   1134: sastore
/*    */     //   1135: iload #6
/*    */     //   1137: istore_1
/*    */     //   1138: aload_0
/*    */     //   1139: getfield A : I
/*    */     //   1142: iconst_1
/*    */     //   1143: isub
/*    */     //   1144: dup
/*    */     //   1145: aload_0
/*    */     //   1146: swap
/*    */     //   1147: putfield A : I
/*    */     //   1150: ifne -> 1043
/*    */     //   1153: iload_3
/*    */     //   1154: iload #4
/*    */     //   1156: aload_0
/*    */     //   1157: iconst_0
/*    */     //   1158: putfield w : I
/*    */     //   1161: aload_0
/*    */     //   1162: iconst_2
/*    */     //   1163: putfield u : I
/*    */     //   1166: iconst_2
/*    */     //   1167: iadd
/*    */     //   1168: aload_0
/*    */     //   1169: swap
/*    */     //   1170: putfield x : I
/*    */     //   1173: ifeq -> 685
/*    */     //   1176: aload_0
/*    */     //   1177: iconst_0
/*    */     //   1178: invokevirtual a : (Z)V
/*    */     //   1181: aload_0
/*    */     //   1182: getfield a : La/d;
/*    */     //   1185: getfield g : I
/*    */     //   1188: ifne -> 685
/*    */     //   1191: iconst_0
/*    */     //   1192: istore_1
/*    */     //   1193: goto -> 1937
/*    */     //   1196: aload_0
/*    */     //   1197: getfield w : I
/*    */     //   1200: ifeq -> 1268
/*    */     //   1203: aload_0
/*    */     //   1204: getfield l : [B
/*    */     //   1207: aload_0
/*    */     //   1208: getfield x : I
/*    */     //   1211: iconst_1
/*    */     //   1212: isub
/*    */     //   1213: baload
/*    */     //   1214: sipush #255
/*    */     //   1217: iand
/*    */     //   1218: istore_2
/*    */     //   1219: aload_0
/*    */     //   1220: iconst_0
/*    */     //   1221: iload_2
/*    */     //   1222: invokevirtual a : (II)Z
/*    */     //   1225: ifeq -> 1233
/*    */     //   1228: aload_0
/*    */     //   1229: iconst_0
/*    */     //   1230: invokevirtual a : (Z)V
/*    */     //   1233: aload_0
/*    */     //   1234: getfield x : I
/*    */     //   1237: iconst_1
/*    */     //   1238: iadd
/*    */     //   1239: aload_0
/*    */     //   1240: swap
/*    */     //   1241: putfield x : I
/*    */     //   1244: aload_0
/*    */     //   1245: getfield z : I
/*    */     //   1248: iconst_1
/*    */     //   1249: isub
/*    */     //   1250: aload_0
/*    */     //   1251: swap
/*    */     //   1252: putfield z : I
/*    */     //   1255: aload_0
/*    */     //   1256: getfield a : La/d;
/*    */     //   1259: getfield g : I
/*    */     //   1262: ifne -> 685
/*    */     //   1265: goto -> 1191
/*    */     //   1268: aload_0
/*    */     //   1269: iconst_1
/*    */     //   1270: putfield w : I
/*    */     //   1273: aload_0
/*    */     //   1274: getfield x : I
/*    */     //   1277: iconst_1
/*    */     //   1278: iadd
/*    */     //   1279: aload_0
/*    */     //   1280: swap
/*    */     //   1281: putfield x : I
/*    */     //   1284: aload_0
/*    */     //   1285: getfield z : I
/*    */     //   1288: iconst_1
/*    */     //   1289: isub
/*    */     //   1290: aload_0
/*    */     //   1291: swap
/*    */     //   1292: putfield z : I
/*    */     //   1295: goto -> 685
/*    */     //   1298: iconst_0
/*    */     //   1299: istore_1
/*    */     //   1300: aload_0
/*    */     //   1301: getfield z : I
/*    */     //   1304: sipush #262
/*    */     //   1307: if_icmpge -> 1339
/*    */     //   1310: aload_0
/*    */     //   1311: invokevirtual a : ()V
/*    */     //   1314: aload_0
/*    */     //   1315: getfield z : I
/*    */     //   1318: ifne -> 1339
/*    */     //   1321: aload_0
/*    */     //   1322: iconst_1
/*    */     //   1323: invokevirtual a : (Z)V
/*    */     //   1326: aload_0
/*    */     //   1327: getfield a : La/d;
/*    */     //   1330: getfield g : I
/*    */     //   1333: ifne -> 761
/*    */     //   1336: goto -> 756
/*    */     //   1339: aload_0
/*    */     //   1340: getfield z : I
/*    */     //   1343: iconst_3
/*    */     //   1344: if_icmplt -> 1418
/*    */     //   1347: aload_0
/*    */     //   1348: getfield p : I
/*    */     //   1351: aload_0
/*    */     //   1352: getfield s : I
/*    */     //   1355: ishl
/*    */     //   1356: aload_0
/*    */     //   1357: getfield l : [B
/*    */     //   1360: aload_0
/*    */     //   1361: getfield x : I
/*    */     //   1364: dup
/*    */     //   1365: istore_1
/*    */     //   1366: iconst_2
/*    */     //   1367: iadd
/*    */     //   1368: baload
/*    */     //   1369: sipush #255
/*    */     //   1372: iand
/*    */     //   1373: ixor
/*    */     //   1374: aload_0
/*    */     //   1375: getfield r : I
/*    */     //   1378: iand
/*    */     //   1379: istore_2
/*    */     //   1380: aload_0
/*    */     //   1381: iload_2
/*    */     //   1382: putfield p : I
/*    */     //   1385: aload_0
/*    */     //   1386: getfield o : [S
/*    */     //   1389: dup
/*    */     //   1390: astore_3
/*    */     //   1391: iload_2
/*    */     //   1392: iload_1
/*    */     //   1393: aload_3
/*    */     //   1394: iload_2
/*    */     //   1395: saload
/*    */     //   1396: dup
/*    */     //   1397: istore_2
/*    */     //   1398: ldc 65535
/*    */     //   1400: iand
/*    */     //   1401: istore_3
/*    */     //   1402: aload_0
/*    */     //   1403: getfield n : [S
/*    */     //   1406: iload_1
/*    */     //   1407: aload_0
/*    */     //   1408: getfield k : I
/*    */     //   1411: iand
/*    */     //   1412: iload_2
/*    */     //   1413: sastore
/*    */     //   1414: i2s
/*    */     //   1415: sastore
/*    */     //   1416: iload_3
/*    */     //   1417: istore_1
/*    */     //   1418: iload_1
/*    */     //   1419: i2l
/*    */     //   1420: lconst_0
/*    */     //   1421: lcmp
/*    */     //   1422: ifeq -> 1463
/*    */     //   1425: aload_0
/*    */     //   1426: getfield x : I
/*    */     //   1429: iload_1
/*    */     //   1430: isub
/*    */     //   1431: ldc 65535
/*    */     //   1433: iand
/*    */     //   1434: aload_0
/*    */     //   1435: getfield i : I
/*    */     //   1438: sipush #262
/*    */     //   1441: isub
/*    */     //   1442: if_icmpgt -> 1463
/*    */     //   1445: aload_0
/*    */     //   1446: getfield E : I
/*    */     //   1449: iconst_2
/*    */     //   1450: if_icmpeq -> 1463
/*    */     //   1453: aload_0
/*    */     //   1454: iload_1
/*    */     //   1455: invokevirtual a : (I)I
/*    */     //   1458: aload_0
/*    */     //   1459: swap
/*    */     //   1460: putfield u : I
/*    */     //   1463: aload_0
/*    */     //   1464: getfield u : I
/*    */     //   1467: dup
/*    */     //   1468: istore_2
/*    */     //   1469: iconst_3
/*    */     //   1470: if_icmplt -> 1713
/*    */     //   1473: iload_2
/*    */     //   1474: aload_0
/*    */     //   1475: getfield x : I
/*    */     //   1478: aload_0
/*    */     //   1479: getfield y : I
/*    */     //   1482: isub
/*    */     //   1483: istore_2
/*    */     //   1484: iconst_3
/*    */     //   1485: isub
/*    */     //   1486: istore_3
/*    */     //   1487: aload_0
/*    */     //   1488: iload_2
/*    */     //   1489: iload_3
/*    */     //   1490: invokevirtual a : (II)Z
/*    */     //   1493: istore_2
/*    */     //   1494: aload_0
/*    */     //   1495: getfield z : I
/*    */     //   1498: istore_3
/*    */     //   1499: aload_0
/*    */     //   1500: getfield u : I
/*    */     //   1503: dup
/*    */     //   1504: istore #4
/*    */     //   1506: iload_3
/*    */     //   1507: iload #4
/*    */     //   1509: isub
/*    */     //   1510: istore_3
/*    */     //   1511: aload_0
/*    */     //   1512: iload_3
/*    */     //   1513: putfield z : I
/*    */     //   1516: aload_0
/*    */     //   1517: getfield C : I
/*    */     //   1520: if_icmpgt -> 1653
/*    */     //   1523: iload_3
/*    */     //   1524: iconst_3
/*    */     //   1525: if_icmplt -> 1653
/*    */     //   1528: iload #4
/*    */     //   1530: iconst_1
/*    */     //   1531: isub
/*    */     //   1532: aload_0
/*    */     //   1533: swap
/*    */     //   1534: putfield u : I
/*    */     //   1537: aload_0
/*    */     //   1538: getfield x : I
/*    */     //   1541: dup
/*    */     //   1542: istore_1
/*    */     //   1543: iconst_1
/*    */     //   1544: iadd
/*    */     //   1545: istore_3
/*    */     //   1546: aload_0
/*    */     //   1547: iload_3
/*    */     //   1548: putfield x : I
/*    */     //   1551: aload_0
/*    */     //   1552: getfield p : I
/*    */     //   1555: aload_0
/*    */     //   1556: getfield s : I
/*    */     //   1559: ishl
/*    */     //   1560: aload_0
/*    */     //   1561: getfield l : [B
/*    */     //   1564: iload_1
/*    */     //   1565: iconst_3
/*    */     //   1566: iadd
/*    */     //   1567: baload
/*    */     //   1568: sipush #255
/*    */     //   1571: iand
/*    */     //   1572: ixor
/*    */     //   1573: aload_0
/*    */     //   1574: getfield r : I
/*    */     //   1577: iand
/*    */     //   1578: istore #4
/*    */     //   1580: aload_0
/*    */     //   1581: iload #4
/*    */     //   1583: putfield p : I
/*    */     //   1586: aload_0
/*    */     //   1587: getfield o : [S
/*    */     //   1590: dup
/*    */     //   1591: astore #5
/*    */     //   1593: iload #4
/*    */     //   1595: iload_3
/*    */     //   1596: aload #5
/*    */     //   1598: iload #4
/*    */     //   1600: saload
/*    */     //   1601: dup
/*    */     //   1602: istore #4
/*    */     //   1604: ldc 65535
/*    */     //   1606: iand
/*    */     //   1607: istore #5
/*    */     //   1609: aload_0
/*    */     //   1610: getfield n : [S
/*    */     //   1613: iload_3
/*    */     //   1614: aload_0
/*    */     //   1615: getfield k : I
/*    */     //   1618: iand
/*    */     //   1619: iload #4
/*    */     //   1621: sastore
/*    */     //   1622: i2s
/*    */     //   1623: sastore
/*    */     //   1624: aload_0
/*    */     //   1625: getfield u : I
/*    */     //   1628: iconst_1
/*    */     //   1629: isub
/*    */     //   1630: dup
/*    */     //   1631: aload_0
/*    */     //   1632: swap
/*    */     //   1633: putfield u : I
/*    */     //   1636: ifne -> 1537
/*    */     //   1639: iload_1
/*    */     //   1640: iconst_2
/*    */     //   1641: iadd
/*    */     //   1642: aload_0
/*    */     //   1643: swap
/*    */     //   1644: putfield x : I
/*    */     //   1647: iload #5
/*    */     //   1649: istore_1
/*    */     //   1650: goto -> 1756
/*    */     //   1653: aload_0
/*    */     //   1654: getfield x : I
/*    */     //   1657: iload #4
/*    */     //   1659: iadd
/*    */     //   1660: istore_3
/*    */     //   1661: aload_0
/*    */     //   1662: iload_3
/*    */     //   1663: putfield x : I
/*    */     //   1666: aload_0
/*    */     //   1667: iconst_0
/*    */     //   1668: putfield u : I
/*    */     //   1671: aload_0
/*    */     //   1672: getfield l : [B
/*    */     //   1675: dup
/*    */     //   1676: astore #4
/*    */     //   1678: iload_3
/*    */     //   1679: baload
/*    */     //   1680: sipush #255
/*    */     //   1683: iand
/*    */     //   1684: aload_0
/*    */     //   1685: getfield s : I
/*    */     //   1688: ishl
/*    */     //   1689: aload #4
/*    */     //   1691: iload_3
/*    */     //   1692: iconst_1
/*    */     //   1693: iadd
/*    */     //   1694: baload
/*    */     //   1695: sipush #255
/*    */     //   1698: iand
/*    */     //   1699: ixor
/*    */     //   1700: aload_0
/*    */     //   1701: getfield r : I
/*    */     //   1704: iand
/*    */     //   1705: aload_0
/*    */     //   1706: swap
/*    */     //   1707: putfield p : I
/*    */     //   1710: goto -> 1756
/*    */     //   1713: aload_0
/*    */     //   1714: getfield l : [B
/*    */     //   1717: aload_0
/*    */     //   1718: getfield x : I
/*    */     //   1721: baload
/*    */     //   1722: sipush #255
/*    */     //   1725: iand
/*    */     //   1726: istore_2
/*    */     //   1727: aload_0
/*    */     //   1728: iconst_0
/*    */     //   1729: iload_2
/*    */     //   1730: invokevirtual a : (II)Z
/*    */     //   1733: istore_2
/*    */     //   1734: aload_0
/*    */     //   1735: getfield z : I
/*    */     //   1738: iconst_1
/*    */     //   1739: isub
/*    */     //   1740: aload_0
/*    */     //   1741: swap
/*    */     //   1742: putfield z : I
/*    */     //   1745: aload_0
/*    */     //   1746: getfield x : I
/*    */     //   1749: iconst_1
/*    */     //   1750: iadd
/*    */     //   1751: aload_0
/*    */     //   1752: swap
/*    */     //   1753: putfield x : I
/*    */     //   1756: iload_2
/*    */     //   1757: ifeq -> 1300
/*    */     //   1760: aload_0
/*    */     //   1761: iconst_0
/*    */     //   1762: invokevirtual a : (Z)V
/*    */     //   1765: aload_0
/*    */     //   1766: getfield a : La/d;
/*    */     //   1769: getfield g : I
/*    */     //   1772: ifne -> 1300
/*    */     //   1775: goto -> 1191
/*    */     //   1778: ldc 65535
/*    */     //   1780: dup
/*    */     //   1781: istore_1
/*    */     //   1782: aload_0
/*    */     //   1783: getfield d : I
/*    */     //   1786: iconst_5
/*    */     //   1787: isub
/*    */     //   1788: dup
/*    */     //   1789: istore_2
/*    */     //   1790: if_icmple -> 1795
/*    */     //   1793: iload_2
/*    */     //   1794: istore_1
/*    */     //   1795: aload_0
/*    */     //   1796: getfield z : I
/*    */     //   1799: iconst_1
/*    */     //   1800: if_icmpgt -> 1832
/*    */     //   1803: aload_0
/*    */     //   1804: invokevirtual a : ()V
/*    */     //   1807: aload_0
/*    */     //   1808: getfield z : I
/*    */     //   1811: ifne -> 1832
/*    */     //   1814: aload_0
/*    */     //   1815: iconst_1
/*    */     //   1816: invokevirtual a : (Z)V
/*    */     //   1819: aload_0
/*    */     //   1820: getfield a : La/d;
/*    */     //   1823: getfield g : I
/*    */     //   1826: ifne -> 761
/*    */     //   1829: goto -> 756
/*    */     //   1832: aload_0
/*    */     //   1833: getfield x : I
/*    */     //   1836: aload_0
/*    */     //   1837: getfield z : I
/*    */     //   1840: iadd
/*    */     //   1841: dup
/*    */     //   1842: istore_2
/*    */     //   1843: aload_0
/*    */     //   1844: iload_2
/*    */     //   1845: putfield x : I
/*    */     //   1848: aload_0
/*    */     //   1849: iconst_0
/*    */     //   1850: putfield z : I
/*    */     //   1853: aload_0
/*    */     //   1854: getfield t : I
/*    */     //   1857: iload_1
/*    */     //   1858: iadd
/*    */     //   1859: istore_3
/*    */     //   1860: ifeq -> 1868
/*    */     //   1863: iload_2
/*    */     //   1864: iload_3
/*    */     //   1865: if_icmplt -> 1899
/*    */     //   1868: iload_2
/*    */     //   1869: iload_3
/*    */     //   1870: isub
/*    */     //   1871: aload_0
/*    */     //   1872: swap
/*    */     //   1873: putfield z : I
/*    */     //   1876: aload_0
/*    */     //   1877: iload_3
/*    */     //   1878: putfield x : I
/*    */     //   1881: aload_0
/*    */     //   1882: iconst_0
/*    */     //   1883: invokevirtual a : (Z)V
/*    */     //   1886: aload_0
/*    */     //   1887: getfield a : La/d;
/*    */     //   1890: getfield g : I
/*    */     //   1893: ifne -> 1899
/*    */     //   1896: goto -> 1191
/*    */     //   1899: aload_0
/*    */     //   1900: getfield x : I
/*    */     //   1903: aload_0
/*    */     //   1904: getfield t : I
/*    */     //   1907: isub
/*    */     //   1908: aload_0
/*    */     //   1909: getfield i : I
/*    */     //   1912: sipush #262
/*    */     //   1915: isub
/*    */     //   1916: if_icmplt -> 1795
/*    */     //   1919: aload_0
/*    */     //   1920: iconst_0
/*    */     //   1921: invokevirtual a : (Z)V
/*    */     //   1924: aload_0
/*    */     //   1925: getfield a : La/d;
/*    */     //   1928: getfield g : I
/*    */     //   1931: ifne -> 1795
/*    */     //   1934: goto -> 1191
/*    */     //   1937: iload_1
/*    */     //   1938: iconst_2
/*    */     //   1939: if_icmpeq -> 1947
/*    */     //   1942: iload_1
/*    */     //   1943: iconst_3
/*    */     //   1944: if_icmpne -> 1954
/*    */     //   1947: aload_0
/*    */     //   1948: sipush #666
/*    */     //   1951: putfield b : I
/*    */     //   1954: iload_1
/*    */     //   1955: ifeq -> 2354
/*    */     //   1958: iload_1
/*    */     //   1959: iconst_2
/*    */     //   1960: if_icmpne -> 1966
/*    */     //   1963: goto -> 2354
/*    */     //   1966: iload_1
/*    */     //   1967: iconst_1
/*    */     //   1968: if_icmpne -> 2101
/*    */     //   1971: iconst_0
/*    */     //   1972: istore_1
/*    */     //   1973: iconst_0
/*    */     //   1974: istore_2
/*    */     //   1975: iconst_0
/*    */     //   1976: aload_0
/*    */     //   1977: swap
/*    */     //   1978: iconst_3
/*    */     //   1979: invokevirtual b : (II)V
/*    */     //   1982: aload_0
/*    */     //   1983: getfield b0 : I
/*    */     //   1986: dup
/*    */     //   1987: istore_3
/*    */     //   1988: bipush #8
/*    */     //   1990: if_icmple -> 2005
/*    */     //   1993: aload_0
/*    */     //   1994: getfield a0 : S
/*    */     //   1997: aload_0
/*    */     //   1998: swap
/*    */     //   1999: invokevirtual b : (I)V
/*    */     //   2002: goto -> 2019
/*    */     //   2005: iload_3
/*    */     //   2006: ifle -> 2019
/*    */     //   2009: aload_0
/*    */     //   2010: getfield a0 : S
/*    */     //   2013: i2b
/*    */     //   2014: aload_0
/*    */     //   2015: swap
/*    */     //   2016: invokevirtual a : (B)V
/*    */     //   2019: iload_2
/*    */     //   2020: aload_0
/*    */     //   2021: iconst_0
/*    */     //   2022: putfield a0 : S
/*    */     //   2025: aload_0
/*    */     //   2026: iconst_0
/*    */     //   2027: putfield b0 : I
/*    */     //   2030: aload_0
/*    */     //   2031: invokevirtual getClass : ()Ljava/lang/Class;
/*    */     //   2034: pop
/*    */     //   2035: i2s
/*    */     //   2036: aload_0
/*    */     //   2037: swap
/*    */     //   2038: invokevirtual b : (I)V
/*    */     //   2041: iconst_m1
/*    */     //   2042: i2s
/*    */     //   2043: aload_0
/*    */     //   2044: swap
/*    */     //   2045: invokevirtual b : (I)V
/*    */     //   2048: aload_0
/*    */     //   2049: getfield l : [B
/*    */     //   2052: iload_1
/*    */     //   2053: aload_0
/*    */     //   2054: getfield c : [B
/*    */     //   2057: aload_0
/*    */     //   2058: getfield f : I
/*    */     //   2061: swap
/*    */     //   2062: swap
/*    */     //   2063: iload_2
/*    */     //   2064: invokestatic arraycopy : (Ljava/lang/Object;ILjava/lang/Object;II)V
/*    */     //   2067: aload_0
/*    */     //   2068: getfield f : I
/*    */     //   2071: aload_0
/*    */     //   2072: swap
/*    */     //   2073: putfield f : I
/*    */     //   2076: aload_0
/*    */     //   2077: getfield a : La/d;
/*    */     //   2080: invokevirtual c : ()V
/*    */     //   2083: aload_0
/*    */     //   2084: getfield a : La/d;
/*    */     //   2087: getfield g : I
/*    */     //   2090: ifne -> 2101
/*    */     //   2093: aload_0
/*    */     //   2094: invokevirtual getClass : ()Ljava/lang/Class;
/*    */     //   2097: pop
/*    */     //   2098: goto -> 2369
/*    */     //   2101: aload_0
/*    */     //   2102: getfield g : I
/*    */     //   2105: dup
/*    */     //   2106: istore_1
/*    */     //   2107: ifgt -> 2113
/*    */     //   2110: goto -> 2369
/*    */     //   2113: iload_1
/*    */     //   2114: iconst_2
/*    */     //   2115: if_icmpne -> 2276
/*    */     //   2118: aload_0
/*    */     //   2119: getfield a : La/d;
/*    */     //   2122: getfield j : La/a;
/*    */     //   2125: invokevirtual a : ()J
/*    */     //   2128: dup2
/*    */     //   2129: dup2
/*    */     //   2130: dup2
/*    */     //   2131: ldc2_w 255
/*    */     //   2134: land
/*    */     //   2135: l2i
/*    */     //   2136: i2b
/*    */     //   2137: aload_0
/*    */     //   2138: swap
/*    */     //   2139: invokevirtual a : (B)V
/*    */     //   2142: bipush #8
/*    */     //   2144: lshr
/*    */     //   2145: ldc2_w 255
/*    */     //   2148: land
/*    */     //   2149: l2i
/*    */     //   2150: i2b
/*    */     //   2151: aload_0
/*    */     //   2152: swap
/*    */     //   2153: invokevirtual a : (B)V
/*    */     //   2156: bipush #16
/*    */     //   2158: lshr
/*    */     //   2159: ldc2_w 255
/*    */     //   2162: land
/*    */     //   2163: l2i
/*    */     //   2164: i2b
/*    */     //   2165: aload_0
/*    */     //   2166: swap
/*    */     //   2167: invokevirtual a : (B)V
/*    */     //   2170: bipush #24
/*    */     //   2172: lshr
/*    */     //   2173: ldc2_w 255
/*    */     //   2176: land
/*    */     //   2177: l2i
/*    */     //   2178: i2b
/*    */     //   2179: aload_0
/*    */     //   2180: swap
/*    */     //   2181: invokevirtual a : (B)V
/*    */     //   2184: aload_0
/*    */     //   2185: getfield a : La/d;
/*    */     //   2188: getfield d : J
/*    */     //   2191: ldc2_w 255
/*    */     //   2194: land
/*    */     //   2195: l2i
/*    */     //   2196: i2b
/*    */     //   2197: aload_0
/*    */     //   2198: swap
/*    */     //   2199: invokevirtual a : (B)V
/*    */     //   2202: aload_0
/*    */     //   2203: getfield a : La/d;
/*    */     //   2206: getfield d : J
/*    */     //   2209: bipush #8
/*    */     //   2211: lshr
/*    */     //   2212: ldc2_w 255
/*    */     //   2215: land
/*    */     //   2216: l2i
/*    */     //   2217: i2b
/*    */     //   2218: aload_0
/*    */     //   2219: swap
/*    */     //   2220: invokevirtual a : (B)V
/*    */     //   2223: aload_0
/*    */     //   2224: getfield a : La/d;
/*    */     //   2227: getfield d : J
/*    */     //   2230: bipush #16
/*    */     //   2232: lshr
/*    */     //   2233: ldc2_w 255
/*    */     //   2236: land
/*    */     //   2237: l2i
/*    */     //   2238: i2b
/*    */     //   2239: aload_0
/*    */     //   2240: swap
/*    */     //   2241: invokevirtual a : (B)V
/*    */     //   2244: aload_0
/*    */     //   2245: getfield a : La/d;
/*    */     //   2248: getfield d : J
/*    */     //   2251: bipush #24
/*    */     //   2253: lshr
/*    */     //   2254: ldc2_w 255
/*    */     //   2257: land
/*    */     //   2258: l2i
/*    */     //   2259: i2b
/*    */     //   2260: aload_0
/*    */     //   2261: swap
/*    */     //   2262: invokevirtual a : (B)V
/*    */     //   2265: aload_0
/*    */     //   2266: invokevirtual b : ()La/e;
/*    */     //   2269: invokevirtual getClass : ()Ljava/lang/Class;
/*    */     //   2272: pop
/*    */     //   2273: goto -> 2328
/*    */     //   2276: aload_0
/*    */     //   2277: getfield a : La/d;
/*    */     //   2280: getfield j : La/a;
/*    */     //   2283: invokevirtual a : ()J
/*    */     //   2286: dup2
/*    */     //   2287: bipush #16
/*    */     //   2289: lushr
/*    */     //   2290: l2i
/*    */     //   2291: dup
/*    */     //   2292: bipush #8
/*    */     //   2294: ishr
/*    */     //   2295: i2b
/*    */     //   2296: aload_0
/*    */     //   2297: swap
/*    */     //   2298: invokevirtual a : (B)V
/*    */     //   2301: i2b
/*    */     //   2302: aload_0
/*    */     //   2303: swap
/*    */     //   2304: invokevirtual a : (B)V
/*    */     //   2307: ldc2_w 65535
/*    */     //   2310: land
/*    */     //   2311: l2i
/*    */     //   2312: dup
/*    */     //   2313: bipush #8
/*    */     //   2315: ishr
/*    */     //   2316: i2b
/*    */     //   2317: aload_0
/*    */     //   2318: swap
/*    */     //   2319: invokevirtual a : (B)V
/*    */     //   2322: i2b
/*    */     //   2323: aload_0
/*    */     //   2324: swap
/*    */     //   2325: invokevirtual a : (B)V
/*    */     //   2328: aload_0
/*    */     //   2329: getfield a : La/d;
/*    */     //   2332: invokevirtual c : ()V
/*    */     //   2335: aload_0
/*    */     //   2336: getfield g : I
/*    */     //   2339: dup
/*    */     //   2340: istore_1
/*    */     //   2341: ifle -> 2369
/*    */     //   2344: iload_1
/*    */     //   2345: ineg
/*    */     //   2346: aload_0
/*    */     //   2347: swap
/*    */     //   2348: putfield g : I
/*    */     //   2351: goto -> 2369
/*    */     //   2354: aload_0
/*    */     //   2355: getfield a : La/d;
/*    */     //   2358: getfield g : I
/*    */     //   2361: ifne -> 2369
/*    */     //   2364: aload_0
/*    */     //   2365: invokevirtual getClass : ()Ljava/lang/Class;
/*    */     //   2368: pop
/*    */     //   2369: return
/*    */     // Line number table:
/*    */     //   Java source line number -> byte code offset
/*    */     //   #1	-> 1
/*    */     //   #2	-> 11
/*    */     //   #8	-> 42
/*    */     //   #14	-> 53
/*    */     //   #18	-> 63
/*    */     //   #19	-> 71
/*    */     //   #20	-> 73
/*    */     //   #21	-> 79
/*    */     //   #23	-> 99
/*    */     //   #24	-> 108
/*    */     //   #27	-> 117
/*    */     //   #30	-> 129
/*    */     //   #34	-> 143
/*    */     //   #41	-> 174
/*    */     //   #42	-> 180
/*    */     //   #43	-> 186
/*    */     //   #44	-> 195
/*    */     //   #45	-> 200
/*    */     //   #46	-> 205
/*    */     //   #47	-> 210
/*    */     //   #48	-> 216
/*    */     //   #49	-> 225
/*    */     //   #51	-> 228
/*    */     //   #52	-> 239
/*    */     //   #53	-> 246
/*    */     //   #54	-> 259
/*    */     //   #55	-> 269
/*    */     //   #56	-> 283
/*    */     //   #57	-> 294
/*    */     //   #58	-> 306
/*    */     //   #59	-> 310
/*    */     //   #60	-> 324
/*    */     //   #61	-> 336
/*    */     //   #64	-> 340
/*    */     //   #65	-> 352
/*    */     //   #66	-> 356
/*    */     //   #67	-> 370
/*    */     //   #68	-> 382
/*    */     //   #69	-> 388
/*    */     //   #70	-> 392
/*    */     //   #73	-> 408
/*    */     //   #74	-> 424
/*    */     //   #78	-> 451
/*    */     //   #79	-> 465
/*    */     //   #81	-> 476
/*    */     //   #82	-> 485
/*    */     //   #83	-> 491
/*    */     //   #84	-> 495
/*    */     //   #85	-> 502
/*    */     //   #86	-> 523
/*    */     //   #87	-> 529
/*    */     //   #88	-> 544
/*    */     //   #89	-> 550
/*    */     //   #90	-> 554
/*    */     //   #95	-> 564
/*    */     //   #96	-> 571
/*    */     //   #97	-> 578
/*    */     //   #103	-> 588
/*    */     //   #111	-> 596
/*    */     //   #118	-> 604
/*    */     //   #124	-> 629
/*    */     //   #127	-> 654
/*    */     //   #128	-> 686
/*    */     //   #129	-> 696
/*    */     //   #130	-> 700
/*    */     //   #231	-> 707
/*    */     //   #232	-> 714
/*    */     //   #233	-> 738
/*    */     //   #235	-> 743
/*    */     //   #237	-> 747
/*    */     //   #238	-> 767
/*    */     //   #239	-> 775
/*    */     //   #241	-> 813
/*    */     //   #242	-> 830
/*    */     //   #243	-> 842
/*    */     //   #247	-> 847
/*    */     //   #248	-> 867
/*    */     //   #250	-> 875
/*    */     //   #257	-> 902
/*    */     //   #258	-> 911
/*    */     //   #262	-> 920
/*    */     //   #268	-> 959
/*    */     //   #274	-> 963
/*    */     //   #275	-> 982
/*    */     //   #280	-> 997
/*    */     //   #286	-> 1015
/*    */     //   #287	-> 1040
/*    */     //   #289	-> 1044
/*    */     //   #290	-> 1066
/*    */     //   #292	-> 1100
/*    */     //   #293	-> 1121
/*    */     //   #294	-> 1134
/*    */     //   #297	-> 1139
/*    */     //   #298	-> 1158
/*    */     //   #299	-> 1163
/*    */     //   #300	-> 1170
/*    */     //   #303	-> 1178
/*    */     //   #304	-> 1182
/*    */     //   #306	-> 1197
/*    */     //   #312	-> 1204
/*    */     //   #315	-> 1230
/*    */     //   #317	-> 1234
/*    */     //   #318	-> 1245
/*    */     //   #319	-> 1256
/*    */     //   #324	-> 1270
/*    */     //   #325	-> 1274
/*    */     //   #326	-> 1285
/*    */     //   #327	-> 1301
/*    */     //   #328	-> 1311
/*    */     //   #329	-> 1315
/*    */     //   #411	-> 1323
/*    */     //   #412	-> 1327
/*    */     //   #413	-> 1340
/*    */     //   #414	-> 1348
/*    */     //   #417	-> 1386
/*    */     //   #418	-> 1403
/*    */     //   #419	-> 1415
/*    */     //   #425	-> 1426
/*    */     //   #431	-> 1446
/*    */     //   #432	-> 1455
/*    */     //   #436	-> 1464
/*    */     //   #439	-> 1475
/*    */     //   #441	-> 1495
/*    */     //   #445	-> 1517
/*    */     //   #447	-> 1534
/*    */     //   #449	-> 1538
/*    */     //   #451	-> 1552
/*    */     //   #453	-> 1587
/*    */     //   #454	-> 1610
/*    */     //   #455	-> 1623
/*    */     //   #460	-> 1625
/*    */     //   #461	-> 1644
/*    */     //   #464	-> 1654
/*    */     //   #465	-> 1668
/*    */     //   #466	-> 1672
/*    */     //   #468	-> 1685
/*    */     //   #476	-> 1714
/*    */     //   #477	-> 1735
/*    */     //   #478	-> 1746
/*    */     //   #482	-> 1762
/*    */     //   #483	-> 1766
/*    */     //   #484	-> 1783
/*    */     //   #491	-> 1796
/*    */     //   #492	-> 1804
/*    */     //   #493	-> 1808
/*    */     //   #520	-> 1816
/*    */     //   #521	-> 1820
/*    */     //   #522	-> 1833
/*    */     //   #523	-> 1850
/*    */     //   #526	-> 1854
/*    */     //   #529	-> 1873
/*    */     //   #530	-> 1878
/*    */     //   #532	-> 1883
/*    */     //   #533	-> 1887
/*    */     //   #539	-> 1900
/*    */     //   #540	-> 1921
/*    */     //   #541	-> 1925
/*    */     //   #542	-> 1951
/*    */     //   #543	-> 1979
/*    */     //   #544	-> 1983
/*    */     //   #545	-> 1994
/*    */     //   #547	-> 2010
/*    */     //   #549	-> 2022
/*    */     //   #550	-> 2027
/*    */     //   #551	-> 2031
/*    */     //   #554	-> 2038
/*    */     //   #555	-> 2045
/*    */     //   #562	-> 2049
/*    */     //   #563	-> 2054
/*    */     //   #564	-> 2068
/*    */     //   #565	-> 2077
/*    */     //   #566	-> 2084
/*    */     //   #567	-> 2094
/*    */     //   #574	-> 2102
/*    */     //   #577	-> 2119
/*    */     //   #578	-> 2139
/*    */     //   #579	-> 2153
/*    */     //   #580	-> 2167
/*    */     //   #581	-> 2181
/*    */     //   #582	-> 2185
/*    */     //   #583	-> 2203
/*    */     //   #584	-> 2224
/*    */     //   #585	-> 2245
/*    */     //   #587	-> 2266
/*    */     //   #591	-> 2277
/*    */     //   #592	-> 2298
/*    */     //   #593	-> 2304
/*    */     //   #594	-> 2319
/*    */     //   #595	-> 2325
/*    */     //   #596	-> 2329
/*    */     //   #601	-> 2336
/*    */     //   #602	-> 2355
/*    */     //   #603	-> 2365
/*    */     // Exception table:
/*    */     //   from	to	target	type
/*    */     //   72	76	95	finally
/*    */     //   79	82	95	finally
/*    */     //   84	95	95	finally
/*  3 */     //   98	102	95	finally } public final void c() { c c2; int j, k; if ((j = (c2 = this.i).f) > (k = this.g)) j = k;  if (j == 0)
/*    */       return;  int i;
/*    */     byte[] arrayOfByte2, arrayOfByte3;
/*  6 */     if ((arrayOfByte2 = c2.c).length > (i = c2.e) && (arrayOfByte3 = this.e).length > this.f && arrayOfByte2.length >= i + j) arrayOfByte3.length;
/*    */ 
/*    */ 
/*    */ 
/*    */ 
/*    */ 
/*    */ 
/*    */ 
/*    */     
/* 15 */     byte[] arrayOfByte1 = this.e; System.arraycopy(arrayOfByte2, i, this, this.f, j);
/*    */ 
/*    */     
/* 18 */     this.f += j; c c1;
/* 19 */     (c1 = this.i).e += j;
/* 20 */     this.h += j;
/* 21 */     this.g -= j; if ((this
/* 22 */       .f -= j) == 0) this
/*    */         
/* 24 */         .e = 0;  } public final void b() { this(this); c c1; byte b1 = 0, b2 = 6; boolean bool = true; byte b3 = 11; this.i = c1; c1.g = bool; c1.j = b3; c1.i = 2048; c1.k = 2047; c1.q = 32768; c1.r = 32767; c1.s = 5; c1.l = new byte[4096]; c1.n = new short[2048]; c1.o = new short[32768]; c1.U = 16384; c1.c = new byte[49152]; c1.d = 49152;
/* 25 */     c1.W = 16384;
/* 26 */     c1.T = new byte[16384]; c1
/*    */       
/* 28 */       .D = b2; c1
/*    */       
/* 30 */       .E = b1;
/* 31 */     this.h = 0L; this.d = 0L; c1
/*    */ 
/*    */ 
/*    */       
/* 35 */       .f = 0; c1
/* 36 */       .e = 0; c1
/*    */ 
/*    */ 
/*    */ 
/*    */       
/* 41 */       .b = 42;
/* 42 */     this.j.b();
/* 43 */     c1.K.a = c1.H; c1.K
/* 44 */       .c = f.h;
/*    */     
/* 46 */     c1.L.a = c1.I; c1.L
/* 47 */       .c = f.i;
/*    */     
/* 49 */     c1.M.a = c1.J; c1.M
/* 50 */       .c = f.j; c1
/*    */       
/* 52 */       .a0 = 0; c1
/* 53 */       .b0 = 0; c1
/*    */ 
/*    */ 
/*    */       
/* 57 */       .c();
/* 58 */     c1.m = c1.i * 2; c1
/*    */       
/* 60 */       .o[c1.q - 1] = 0; b1 = 0; while (b1 < c1
/* 61 */       .q - 1) { c1
/* 62 */         .o[b1] = 0; b1++; }
/*    */ 
/*    */ 
/*    */     
/* 66 */     c1.C = (c.d0[c1.D]).b;
/* 67 */     c1.F = (c.d0[c1.D]).a;
/* 68 */     c1.G = (c.d0[c1.D]).c;
/* 69 */     c1.B = (c.d0[c1.D]).d; c1
/*    */       
/* 71 */       .x = 0; c1
/* 72 */       .t = 0; c1
/* 73 */       .z = 0; c1
/* 74 */       .A = 2; c1.u = 2; c1
/* 75 */       .w = 0; c1
/* 76 */       .p = 0; }
/*    */    }


/* Location:              C:\Users\Omen\Downloads\app lucky printer\android-printing-sdk-demo-doc\android-printing-sdk-demo\app\libs\test\classes.jar!\a\d.class
 * Java compiler version: 8 (52.0)
 * JD-Core Version:       1.1.3
 */